fastapirichlogger/__init__.py
fastapirichlogger/logger.py
fastapirichlogger/setup.py
fastapirichlogger/core/__init__.py
fastapirichlogger/core/config.py
fastapirichlogger-0.1.4.dist-info/METADATA
fastapirichlogger-0.1.4.dist-info/WHEEL
fastapirichlogger-0.1.4.dist-info/top_level.txt
fastapirichlogger-0.1.4.dist-info/RECORD
