Metadata-Version: 2.1
Name: fastapirichlogger
Version: 0.1.4
Summary: An awesome logger for FastAPI.
Home-page: https://github.com/kevinqz/fastapirichlogger
Author: Kevin Saltarelli
Author-email: kevinqz@gmail.com
License: LICENSE.md
Requires-Dist: fastapi
Requires-Dist: rich
